[
  { "fullname": "Rosalind Brewitt", "numero": "954-744-2595" },
  { "fullname": "Zarla Alexsandrev", "numero": "721-793-4566" },
  { "fullname": "Olenka Palphreyman", "numero": "361-822-7663" },
  { "fullname": "Sigvard Schmuhl", "numero": "465-964-2902" },
  { "fullname": "Jory Redmore", "numero": "370-972-1288" },
  { "fullname": "Granville Zimmerman", "numero": "200-488-2735" },
  { "fullname": "Dex Darragon", "numero": "203-603-3904" },
  { "fullname": "Gwenora Clampett", "numero": "383-930-4373" },
  { "fullname": "Mohammed Beccero", "numero": "538-328-7147" },
  { "fullname": "Olag Bousler", "numero": "404-800-8449" },
  { "fullname": "Jermaine Willan", "numero": "710-359-5012" },
  { "fullname": "Lanette Habin", "numero": "159-165-3251" },
  { "fullname": "Gaylor Spinke", "numero": "149-942-3602" },
  { "fullname": "Friedrick Dishmon", "numero": "495-593-3385" },
  { "fullname": "Lorelle Bullon", "numero": "803-168-4419" },
  { "fullname": "Wayland Jezard", "numero": "852-767-7000" },
  { "fullname": "Valeda Sussex", "numero": "183-799-3934" },
  { "fullname": "Chelsy Houlridge", "numero": "168-262-2439" },
  { "fullname": "Gracia Dwelly", "numero": "890-872-8227" },
  { "fullname": "Dud Neville", "numero": "587-518-6618" },
  { "fullname": "Brion Enser", "numero": "646-923-3238" },
  { "fullname": "Scottie Stilly", "numero": "657-968-3343" },
  { "fullname": "Sukey Colbourne", "numero": "856-512-3470" },
  { "fullname": "Lydia Dykes", "numero": "453-259-8209" },
  { "fullname": "Sharia Smallpeace", "numero": "250-204-1370" },
  { "fullname": "Barty Dinneen", "numero": "882-295-3369" },
  { "fullname": "Janina Starsmore", "numero": "848-807-3877" },
  { "fullname": "Brandais Gonneau", "numero": "578-559-0966" },
  { "fullname": "Catherin Djordjevic", "numero": "720-916-0850" },
  { "fullname": "Hanson Britee", "numero": "310-794-1294" },
  { "fullname": "Clovis Klimschak", "numero": "820-437-1434" },
  { "fullname": "Rem Ebi", "numero": "168-985-9038" },
  { "fullname": "Debbie Collman", "numero": "462-178-9882" },
  { "fullname": "Nerty Dunnet", "numero": "283-488-2093" },
  { "fullname": "Valina Kearford", "numero": "628-670-3732" },
  { "fullname": "Verney Cordes", "numero": "262-550-3983" },
  { "fullname": "August Eddies", "numero": "528-496-3695" },
  { "fullname": "Giselle Pamphilon", "numero": "458-778-9651" },
  { "fullname": "Thor Instone", "numero": "609-671-4676" },
  { "fullname": "Brandi Macias", "numero": "539-454-9776" },
  { "fullname": "Kalie Nevison", "numero": "609-847-3574" },
  { "fullname": "Devin South", "numero": "567-416-9125" },
  { "fullname": "Matteo Stout", "numero": "171-771-7022" },
  { "fullname": "Val Derrick", "numero": "529-811-0023" },
  { "fullname": "Beth felip", "numero": "910-522-0906" },
  { "fullname": "Lizzie Knibbs", "numero": "489-862-5653" },
  { "fullname": "Stacee Pick", "numero": "333-683-4524" },
  { "fullname": "Dorree Goodenough", "numero": "617-384-8484" },
  { "fullname": "Essie Eaklee", "numero": "856-887-1107" },
  { "fullname": "Zora Le Guin", "numero": "613-914-6101" },
  { "fullname": "Hali Scarman", "numero": "524-114-2459" },
  { "fullname": "Grannie Booker", "numero": "234-455-4349" },
  { "fullname": "Rachelle Berrigan", "numero": "757-170-0430" },
  { "fullname": "Binny Instone", "numero": "459-850-0890" },
  { "fullname": "Elfrieda Lawful", "numero": "637-344-9933" },
  { "fullname": "Kally Ruzek", "numero": "209-430-3507" },
  { "fullname": "Gizela Pamment", "numero": "511-230-8897" },
  { "fullname": "Brandi Feldstern", "numero": "562-248-0337" },
  { "fullname": "Babette Celier", "numero": "892-992-0831" },
  { "fullname": "Nerissa Planks", "numero": "833-641-4058" },
  { "fullname": "Yves Jacobson", "numero": "742-625-8834" },
  { "fullname": "Torry Sackler", "numero": "295-252-0111" },
  { "fullname": "Chantalle De Miranda", "numero": "915-612-0912" },
  { "fullname": "Marthena Radbone", "numero": "244-533-0529" },
  { "fullname": "Karla Livingston", "numero": "375-474-8959" },
  { "fullname": "Hilliary Martinuzzi", "numero": "164-534-6201" },
  { "fullname": "Crosby Bartosinski", "numero": "123-731-5304" },
  { "fullname": "Kamilah Izachik", "numero": "222-623-2182" },
  { "fullname": "Horacio Willingam", "numero": "522-953-4749" },
  { "fullname": "Cory Beaudry", "numero": "237-680-2202" },
  { "fullname": "Lind Ondrusek", "numero": "618-715-8821" },
  { "fullname": "Emile Di Giacomo", "numero": "912-950-3684" },
  { "fullname": "Vi Frowde", "numero": "880-326-1941" },
  { "fullname": "Elisabetta Giacomucci", "numero": "827-394-9668" },
  { "fullname": "Dorothy Neylon", "numero": "776-295-6386" },
  { "fullname": "Agnes Trippett", "numero": "706-103-3747" },
  { "fullname": "Kearney Bowden", "numero": "855-602-3429" },
  { "fullname": "Garret Maurice", "numero": "401-681-3665" },
  { "fullname": "Barton Rehor", "numero": "403-516-4822" },
  { "fullname": "Vinnie Calender", "numero": "715-617-5328" },
  { "fullname": "Ingar MacDunlevy", "numero": "543-743-8647" },
  { "fullname": "Lauralee Shipston", "numero": "939-934-8794" },
  { "fullname": "Raviv Barde", "numero": "811-522-8723" },
  { "fullname": "Anna-diane Twinning", "numero": "139-166-5303" },
  { "fullname": "Ruprecht Shawyer", "numero": "480-170-5204" },
  { "fullname": "Sybilla Crowcher", "numero": "510-540-8249" },
  { "fullname": "Brietta O'Boyle", "numero": "304-897-0096" },
  { "fullname": "Hilarius Cabble", "numero": "981-902-1995" },
  { "fullname": "Vanessa Mattisson", "numero": "390-975-7687" },
  { "fullname": "Allister Thon", "numero": "974-877-9292" },
  { "fullname": "Sianna Hugh", "numero": "147-975-6460" },
  { "fullname": "Lonnard Danielis", "numero": "845-447-3784" },
  { "fullname": "Gaven Kidwell", "numero": "554-546-6004" },
  { "fullname": "Hestia Heiton", "numero": "596-465-5549" },
  { "fullname": "Zarla Loxley", "numero": "997-110-9824" },
  { "fullname": "Elyssa Henworth", "numero": "921-755-0174" },
  { "fullname": "Conrad St Pierre", "numero": "587-123-3619" },
  { "fullname": "Ottilie Glisane", "numero": "855-340-1579" },
  { "fullname": "Arron Tebald", "numero": "795-583-8555" },
  { "fullname": "Ryann McChruiter", "numero": "403-800-9853" }
]
